hcs_ext_vsphere/__init__.py
hcs_ext_vsphere/provider/__init__.py
hcs_ext_vsphere/provider/folder.py
hcs_ext_vsphere/provider/lib_ovf.py
hcs_ext_vsphere/provider/pool.py
hcs_ext_vsphere/provider/vm.py
hcs_ext_vsphere/provider/runtime/__init__.py
hcs_ext_vsphere/provider/runtime/find_mor.py
hcs_ext_vsphere/provider/runtime/info.py
hcs_ext_vsphere/provider/vc/__init__.py
hcs_ext_vsphere/provider/vc/contentlib.py
hcs_ext_vsphere/provider/vc/datacenter.py
hcs_ext_vsphere/provider/vc/datastore.py
hcs_ext_vsphere/provider/vc/folder.py
hcs_ext_vsphere/provider/vc/govc.py
hcs_ext_vsphere/provider/vc/network.py
hcs_ext_vsphere/provider/vc/pool.py
hcs_ext_vsphere/provider/vc/service.py
hcs_ext_vsphere/provider/vc/vm.py
hcs_ext_vsphere/templates/__init__.py
hcs_ext_vsphere-0.0.8.dist-info/METADATA
hcs_ext_vsphere-0.0.8.dist-info/WHEEL
hcs_ext_vsphere-0.0.8.dist-info/top_level.txt
hcs_ext_vsphere-0.0.8.dist-info/RECORD
